[
  {
    "type": "RECTANGLE",
    "id": "P01L03",
    "pageNumber": "1",
    "x": 99,
    "y": 366,
    "width": 393,
    "height": 349,
    "rotation": 0
  },
  {
    "type": "TEXT",
    "id": "P01L03",
    "rotation": 0,
    "textAlignment": {
      "horizontal": "LEFT",
      "vertical": "CENTER"
    },
    "textProperties": {
      "fontName": "Urbanist",
      "fontSize": 14,
      "isBold": false
    },
    "color": [
      "#007580"
    ]
  },
  {
    "type": "RECTANGLE",
    "id": "P01L02",
    "pageNumber": "1",
    "x": 92,
    "y": 266,
    "width": 404,
    "height": 45,
    "rotation": 0
  },
  {
    "type": "TEXT",
    "id": "P01L02",
    "rotation": 0,
    "textAlignment": {
      "horizontal": "CENTER",
      "vertical": "CENTER"
    },
    "textProperties": {
      "fontName": "Urbanist",
      "fontSize": 33,
      "isBold": true
    },
    "color": [
      "#00c6c1"
    ]
  },
  {
    "type": "RECTANGLE",
    "id": "P01L01",
    "pageNumber": "1",
    "x": 92,
    "y": 152,
    "width": 404,
    "height": 108,
    "rotation": 0
  },
  {
    "type": "TEXT",
    "id": "P01L01",
    "rotation": 0,
    "textAlignment": {
      "horizontal": "CENTER",
      "vertical": "CENTER"
    },
    "textProperties": {
      "fontName": "Urbanist",
      "fontSize": 42,
      "isBold": true
    },
    "color": [
      "#e90000"
    ]
  },
  {
    "type": "RECTANGLE",
    "id": "P02L04",
    "pageNumber": "2",
    "x": 145,
    "y": 443,
    "width": 305,
    "height": 44,
    "rotation": 0
  },
  {
    "type": "TEXT",
    "id": "P02L04",
    "rotation": 0,
    "textAlignment": {
      "horizontal": "CENTER",
      "vertical": "CENTER"
    },
    "textProperties": {
      "fontName": "Urbanist",
      "fontSize": 23,
      "isBold": true
    },
    "color": [
      "#00c6c1"
    ]
  },
  {
    "type": "RECTANGLE",
    "id": "P02L03",
    "pageNumber": "2",
    "x": 145,
    "y": 319,
    "width": 305,
    "height": 88,
    "rotation": 0
  },
  {
    "type": "TEXT",
    "id": "P02L03",
    "rotation": 0,
    "textAlignment": {
      "horizontal": "CENTER",
      "vertical": "CENTER"
    },
    "textProperties": {
      "fontName": "Urbanist",
      "fontSize": 33,
      "isBold": true
    },
    "color": [
      "#00c6c1"
    ]
  },
  {
    "type": "RECTANGLE",
    "id": "P02L02",
    "pageNumber": "2",
    "x": 413,
    "y": 89,
    "width": 163,
    "height": 32,
    "rotation": 0
  },
  {
    "type": "TEXT",
    "id": "P02L02",
    "rotation": 0,
    "textAlignment": {
      "horizontal": "RIGHT",
      "vertical": "CENTER"
    },
    "textProperties": {
      "fontName": "Urbanist",
      "fontSize": 17,
      "isBold": false
    },
    "color": [
      "#ffffff"
    ]
  },
  {
    "type": "RECTANGLE",
    "id": "P02L01",
    "pageNumber": "2",
    "x": 413,
    "y": 55,
    "width": 163,
    "height": 32,
    "rotation": 0
  },
  {
    "type": "TEXT",
    "id": "P02L01",
    "rotation": 0,
    "textAlignment": {
      "horizontal": "RIGHT",
      "vertical": "CENTER"
    },
    "textProperties": {
      "fontName": "Urbanist",
      "fontSize": 17,
      "isBold": false
    },
    "color": [
      "#ffffff"
    ]
  },
  {
    "type": "RECTANGLE",
    "id": "P03L12",
    "pageNumber": "3",
    "x": 140,
    "y": 690,
    "width": 379,
    "height": 65,
    "rotation": 0
  },
  {
    "type": "TEXT",
    "id": "P03L12",
    "rotation": 0,
    "textAlignment": {
      "horizontal": "LEFT",
      "vertical": "CENTER"
    },
    "textProperties": {
      "fontName": "Urbanist",
      "fontSize": 14,
      "isBold": false
    },
    "color": [
      "#000000"
    ]
  },
  {
    "type": "RECTANGLE",
    "id": "P03L11",
    "pageNumber": "3",
    "x": 135,
    "y": 648,
    "width": 401,
    "height": 41,
    "rotation": 0
  },
  {
    "type": "TEXT",
    "id": "P03L11",
    "rotation": 0,
    "textAlignment": {
      "horizontal": "LEFT",
      "vertical": "CENTER"
    },
    "textProperties": {
      "fontName": "Urbanist",
      "fontSize": 24,
      "isBold": true
    },
    "color": [
      "#e90000"
    ]
  },
  {
    "type": "RECTANGLE",
    "id": "P03L10",
    "pageNumber": "3",
    "x": 65,
    "y": 635,
    "width": 48,
    "height": 65,
    "rotation": 0
  },
  {
    "type": "TEXT",
    "id": "P03L10",
    "rotation": 0,
    "textAlignment": {
      "horizontal": "RIGHT",
      "vertical": "CENTER"
    },
    "textProperties": {
      "fontName": "Urbanist",
      "fontSize": 65,
      "isBold": true
    },
    "color": [
      "#e90000"
    ]
  },
  {
    "type": "RECTANGLE",
    "id": "P03L09",
    "pageNumber": "3",
    "x": 140,
    "y": 545,
    "width": 379,
    "height": 82,
    "rotation": 0
  },
  {
    "type": "TEXT",
    "id": "P03L09",
    "rotation": 0,
    "textAlignment": {
      "horizontal": "LEFT",
      "vertical": "CENTER"
    },
    "textProperties": {
      "fontName": "Urbanist",
      "fontSize": 14,
      "isBold": false
    },
    "color": [
      "#000000"
    ]
  },
  {
    "type": "RECTANGLE",
    "id": "P03L08",
    "pageNumber": "3",
    "x": 135,
    "y": 478,
    "width": 401,
    "height": 64,
    "rotation": 0
  },
  {
    "type": "TEXT",
    "id": "P03L08",
    "rotation": 0,
    "textAlignment": {
      "horizontal": "LEFT",
      "vertical": "CENTER"
    },
    "textProperties": {
      "fontName": "Urbanist",
      "fontSize": 24,
      "isBold": true
    },
    "color": [
      "#e90000"
    ]
  },
  {
    "type": "RECTANGLE",
    "id": "P03L07",
    "pageNumber": "3",
    "x": 65,
    "y": 477,
    "width": 48,
    "height": 65,
    "rotation": 0
  },
  {
    "type": "TEXT",
    "id": "P03L07",
    "rotation": 0,
    "textAlignment": {
      "horizontal": "RIGHT",
      "vertical": "CENTER"
    },
    "textProperties": {
      "fontName": "Urbanist",
      "fontSize": 65,
      "isBold": true
    },
    "color": [
      "#e90000"
    ]
  },
  {
    "type": "RECTANGLE",
    "id": "P03L06",
    "pageNumber": "3",
    "x": 140,
    "y": 366,
    "width": 379,
    "height": 79,
    "rotation": 0
  },
  {
    "type": "TEXT",
    "id": "P03L06",
    "rotation": 0,
    "textAlignment": {
      "horizontal": "LEFT",
      "vertical": "CENTER"
    },
    "textProperties": {
      "fontName": "Urbanist",
      "fontSize": 14,
      "isBold": false
    },
    "color": [
      "#000000"
    ]
  },
  {
    "type": "RECTANGLE",
    "id": "P03L05",
    "pageNumber": "3",
    "x": 135,
    "y": 298,
    "width": 401,
    "height": 64,
    "rotation": 0
  },
  {
    "type": "TEXT",
    "id": "P03L05",
    "rotation": 0,
    "textAlignment": {
      "horizontal": "LEFT",
      "vertical": "CENTER"
    },
    "textProperties": {
      "fontName": "Urbanist",
      "fontSize": 24,
      "isBold": true
    },
    "color": [
      "#e90000"
    ]
  },
  {
    "type": "RECTANGLE",
    "id": "P03L04",
    "pageNumber": "3",
    "x": 65,
    "y": 297,
    "width": 48,
    "height": 65,
    "rotation": 0
  },
  {
    "type": "TEXT",
    "id": "P03L04",
    "rotation": 0,
    "textAlignment": {
      "horizontal": "RIGHT",
      "vertical": "CENTER"
    },
    "textProperties": {
      "fontName": "Urbanist",
      "fontSize": 65,
      "isBold": true
    },
    "color": [
      "#e90000"
    ]
  },
  {
    "type": "RECTANGLE",
    "id": "P03L03",
    "pageNumber": "3",
    "x": 135,
    "y": 218,
    "width": 401,
    "height": 37,
    "rotation": 0
  },
  {
    "type": "TEXT",
    "id": "P03L03",
    "rotation": 0,
    "textAlignment": {
      "horizontal": "LEFT",
      "vertical": "CENTER"
    },
    "textProperties": {
      "fontName": "Urbanist",
      "fontSize": 24,
      "isBold": true
    },
    "color": [
      "#e90000"
    ]
  },
  {
    "type": "RECTANGLE",
    "id": "P03L02",
    "pageNumber": "3",
    "x": 65,
    "y": 201,
    "width": 48,
    "height": 65,
    "rotation": 0
  },
  {
    "type": "TEXT",
    "id": "P03L02",
    "rotation": 0,
    "textAlignment": {
      "horizontal": "RIGHT",
      "vertical": "CENTER"
    },
    "textProperties": {
      "fontName": "Urbanist",
      "fontSize": 65,
      "isBold": true
    },
    "color": [
      "#e90000"
    ]
  },
  {
    "type": "RECTANGLE",
    "id": "P03L01",
    "pageNumber": "3",
    "x": 145,
    "y": 107,
    "width": 305,
    "height": 65,
    "rotation": 0
  },
  {
    "type": "TEXT",
    "id": "P03L01",
    "rotation": 0,
    "textAlignment": {
      "horizontal": "CENTER",
      "vertical": "CENTER"
    },
    "textProperties": {
      "fontName": "Urbanist",
      "fontSize": 42,
      "isBold": true
    },
    "color": [
      "#00c6c1"
    ]
  },
  {
    "type": "RECTANGLE",
    "id": "P04L08",
    "pageNumber": "4",
    "x": 141,
    "y": 477,
    "width": 379,
    "height": 105,
    "rotation": 0
  },
  {
    "type": "TEXT",
    "id": "P04L08",
    "rotation": 0,
    "textAlignment": {
      "horizontal": "LEFT",
      "vertical": "CENTER"
    },
    "textProperties": {
      "fontName": "Urbanist",
      "fontSize": 14,
      "isBold": false
    },
    "color": [
      "#000000"
    ]
  },
  {
    "type": "RECTANGLE",
    "id": "P04L07",
    "pageNumber": "4",
    "x": 135,
    "y": 427,
    "width": 401,
    "height": 41,
    "rotation": 0
  },
  {
    "type": "TEXT",
    "id": "P04L07",
    "rotation": 0,
    "textAlignment": {
      "horizontal": "LEFT",
      "vertical": "CENTER"
    },
    "textProperties": {
      "fontName": "Urbanist",
      "fontSize": 24,
      "isBold": true
    },
    "color": [
      "#e90000"
    ]
  },
  {
    "type": "RECTANGLE",
    "id": "P04L06",
    "pageNumber": "4",
    "x": 65,
    "y": 414,
    "width": 48,
    "height": 65,
    "rotation": 0
  },
  {
    "type": "TEXT",
    "id": "P04L06",
    "rotation": 0,
    "textAlignment": {
      "horizontal": "CENTER",
      "vertical": "CENTER"
    },
    "textProperties": {
      "fontName": "Urbanist",
      "fontSize": 65,
      "isBold": true
    },
    "color": [
      "#e90000"
    ]
  },
  {
    "type": "RECTANGLE",
    "id": "P04L05",
    "pageNumber": "4",
    "x": 141,
    "y": 267,
    "width": 379,
    "height": 135,
    "rotation": 0
  },
  {
    "type": "TEXT",
    "id": "P04L05",
    "rotation": 0,
    "textAlignment": {
      "horizontal": "LEFT",
      "vertical": "CENTER"
    },
    "textProperties": {
      "fontName": "Urbanist",
      "fontSize": 14,
      "isBold": false
    },
    "color": [
      "#000000"
    ]
  },
  {
    "type": "RECTANGLE",
    "id": "P04L04",
    "pageNumber": "4",
    "x": 135,
    "y": 217,
    "width": 401,
    "height": 41,
    "rotation": 0
  },
  {
    "type": "TEXT",
    "id": "P04L04",
    "rotation": 0,
    "textAlignment": {
      "horizontal": "LEFT",
      "vertical": "CENTER"
    },
    "textProperties": {
      "fontName": "Urbanist",
      "fontSize": 24,
      "isBold": true
    },
    "color": [
      "#e90000"
    ]
  },
  {
    "type": "RECTANGLE",
    "id": "P04L03",
    "pageNumber": "4",
    "x": 65,
    "y": 204,
    "width": 48,
    "height": 65,
    "rotation": 0
  },
  {
    "type": "TEXT",
    "id": "P04L03",
    "rotation": 0,
    "textAlignment": {
      "horizontal": "CENTER",
      "vertical": "CENTER"
    },
    "textProperties": {
      "fontName": "Urbanist",
      "fontSize": 65,
      "isBold": true
    },
    "color": [
      "#e90000"
    ]
  },
  {
    "type": "RECTANGLE",
    "id": "P04L02",
    "pageNumber": "4",
    "x": 135,
    "y": 127,
    "width": 401,
    "height": 41,
    "rotation": 0
  },
  {
    "type": "TEXT",
    "id": "P04L02",
    "rotation": 0,
    "textAlignment": {
      "horizontal": "LEFT",
      "vertical": "CENTER"
    },
    "textProperties": {
      "fontName": "Urbanist",
      "fontSize": 24,
      "isBold": true
    },
    "color": [
      "#e90000"
    ]
  },
  {
    "type": "RECTANGLE",
    "id": "P04L01",
    "pageNumber": "4",
    "x": 65,
    "y": 111,
    "width": 48,
    "height": 65,
    "rotation": 0
  },
  {
    "type": "TEXT",
    "id": "P04L01",
    "rotation": 0,
    "textAlignment": {
      "horizontal": "CENTER",
      "vertical": "CENTER"
    },
    "textProperties": {
      "fontName": "Urbanist",
      "fontSize": 65,
      "isBold": true
    },
    "color": [
      "#e90000"
    ]
  },
  {
    "type": "RECTANGLE",
    "id": "P05L03",
    "pageNumber": "5",
    "x": 57,
    "y": 359,
    "width": 480,
    "height": 396,
    "rotation": 0
  },
  {
    "type": "TEXT",
    "id": "P05L03",
    "rotation": 0,
    "textAlignment": {
      "horizontal": "JUSTIFIED",
      "vertical": "TOP"
    },
    "textProperties": {
      "fontName": "Urbanist",
      "fontSize": 17,
      "isBold": false
    },
    "color": [
      "#000000"
    ]
  },
  {
    "type": "RECTANGLE",
    "id": "P05L02",
    "pageNumber": "5",
    "x": 57,
    "y": 309,
    "width": 480,
    "height": 32,
    "rotation": 0
  },
  {
    "type": "TEXT",
    "id": "P05L02",
    "rotation": 0,
    "textAlignment": {
      "horizontal": "CENTER",
      "vertical": "CENTER"
    },
    "textProperties": {
      "fontName": "Urbanist",
      "fontSize": 18,
      "isBold": true
    },
    "color": [
      "#000000"
    ]
  },
  {
    "type": "RECTANGLE",
    "id": "P05L01",
    "pageNumber": "5",
    "x": 44,
    "y": 117,
    "width": 511,
    "height": 148,
    "rotation": 0
  },
  {
    "type": "TEXT",
    "id": "P05L01",
    "rotation": 0,
    "textAlignment": {
      "horizontal": "CENTER",
      "vertical": "CENTER"
    },
    "textProperties": {
      "fontName": "Urbanist",
      "fontSize": 18,
      "isBold": false
    },
    "color": [
      "#ffffff"
    ]
  },
  {
    "type": "INSTANCE",
    "id": "fond",
    "pageNumber": "5",
    "x": 0,
    "y": 0,
    "width": 595,
    "height": 842,
    "rotation": 0
  },
  {
    "type": "RECTANGLE",
    "id": "logo-fr 1",
    "pageNumber": null,
    "x": 427,
    "y": 14,
    "width": 116,
    "height": 32,
    "rotation": 0
  },
  {
    "type": "GROUP",
    "id": "Group 5",
    "pageNumber": null,
    "x": 0,
    "y": -67.551025390625,
    "width": 595,
    "height": 909.551025390625,
    "rotation": 0
  },
  {
    "type": "GROUP",
    "id": "right leg",
    "pageNumber": null,
    "x": 595,
    "y": 709,
    "width": 92.12550354003906,
    "height": 132.8390350341797,
    "rotation": -180
  },
  {
    "type": "VECTOR",
    "id": "blue",
    "pageNumber": null,
    "x": 582.3698883056641,
    "y": 841.8390045166016,
    "width": 132.8390350341797,
    "height": 12.630108833312988,
    "rotation": 90.00000000000001
  },
  {
    "type": "VECTOR",
    "id": "red",
    "pageNumber": null,
    "x": 595.0000058679534,
    "y": 829.2089233398438,
    "width": 92.12550354003906,
    "height": 12.630108833312988,
    "rotation": -180
  },
  {
    "type": "GROUP",
    "id": "left leg",
    "pageNumber": null,
    "x": 0,
    "y": 709,
    "width": 92.12550354003906,
    "height": 132.8390350341797,
    "rotation": 0
  },
  {
    "type": "VECTOR",
    "id": "blue",
    "pageNumber": null,
    "x": 12.630105972290039,
    "y": 841.8390045166016,
    "width": 132.8390350341797,
    "height": 12.630108833312988,
    "rotation": 90
  },
  {
    "type": "VECTOR",
    "id": "red",
    "pageNumber": null,
    "x": 0,
    "y": 829.2089233398438,
    "width": 92.12550354003906,
    "height": 12.630108833312988,
    "rotation": 0
  },
  {
    "type": "BOOLEAN_OPERATION",
    "id": "frame",
    "pageNumber": null,
    "x": 0,
    "y": 842,
    "width": 842,
    "height": 595,
    "rotation": 90
  },
  {
    "type": "RECTANGLE",
    "id": "Rectangle 4",
    "pageNumber": null,
    "x": 13.000000000000002,
    "y": 828.9935703277588,
    "width": 816.4036254882812,
    "height": 569,
    "rotation": 90
  },
  {
    "type": "RECTANGLE",
    "id": "Rectangle 3",
    "pageNumber": null,
    "x": 0,
    "y": 842,
    "width": 842,
    "height": 595,
    "rotation": 90
  },
  {
    "type": "GROUP",
    "id": "Group 1",
    "pageNumber": null,
    "x": 581.135009765625,
    "y": -67.551025390625,
    "width": 193.1349639892578,
    "height": 139.64430236816406,
    "rotation": -180
  },
  {
    "type": "BOOLEAN_OPERATION",
    "id": "Intersect",
    "pageNumber": null,
    "x": 581.135009765625,
    "y": -67.551025390625,
    "width": 193.1349639892578,
    "height": 139.64430236816406,
    "rotation": -180
  },
  {
    "type": "BOOLEAN_OPERATION",
    "id": "Exclude",
    "pageNumber": null,
    "x": 581.1350095319684,
    "y": -67.551025390625,
    "width": 193.1349639892578,
    "height": 139.64430236816406,
    "rotation": -180
  },
  {
    "type": "VECTOR",
    "id": "Ellipse 2",
    "pageNumber": null,
    "x": 575.7223947095807,
    "y": -67.551025390625,
    "width": 187.72235107421875,
    "height": 138.4834747314453,
    "rotation": -180
  },
  {
    "type": "VECTOR",
    "id": "Ellipse 1",
    "pageNumber": null,
    "x": 581.1350095319684,
    "y": -65,
    "width": 192.13497924804688,
    "height": 137.09327697753906,
    "rotation": -180
  },
  {
    "type": "GROUP",
    "id": "Group 5",
    "pageNumber": null,
    "x": 0,
    "y": -67.551025390625,
    "width": 595,
    "height": 909.551025390625,
    "rotation": 0
  },
  {
    "type": "GROUP",
    "id": "right leg",
    "pageNumber": null,
    "x": 595,
    "y": 709,
    "width": 92.12550354003906,
    "height": 132.8390350341797,
    "rotation": -180
  },
  {
    "type": "VECTOR",
    "id": "blue",
    "pageNumber": null,
    "x": 582.3698883056641,
    "y": 841.8390045166016,
    "width": 132.8390350341797,
    "height": 12.630108833312988,
    "rotation": 90.00000000000001
  },
  {
    "type": "VECTOR",
    "id": "red",
    "pageNumber": null,
    "x": 595.0000058679534,
    "y": 829.2089233398438,
    "width": 92.12550354003906,
    "height": 12.630108833312988,
    "rotation": -180
  },
  {
    "type": "GROUP",
    "id": "left leg",
    "pageNumber": null,
    "x": 0,
    "y": 709,
    "width": 92.12550354003906,
    "height": 132.8390350341797,
    "rotation": 0
  },
  {
    "type": "VECTOR",
    "id": "blue",
    "pageNumber": null,
    "x": 12.630105972290039,
    "y": 841.8390045166016,
    "width": 132.8390350341797,
    "height": 12.630108833312988,
    "rotation": 90
  },
  {
    "type": "VECTOR",
    "id": "red",
    "pageNumber": null,
    "x": 0,
    "y": 829.2089233398438,
    "width": 92.12550354003906,
    "height": 12.630108833312988,
    "rotation": 0
  },
  {
    "type": "BOOLEAN_OPERATION",
    "id": "frame",
    "pageNumber": null,
    "x": 0,
    "y": 842,
    "width": 842,
    "height": 595,
    "rotation": 90
  },
  {
    "type": "RECTANGLE",
    "id": "Rectangle 4",
    "pageNumber": null,
    "x": 13.000000000000002,
    "y": 828.9935703277588,
    "width": 816.4036254882812,
    "height": 569,
    "rotation": 90
  },
  {
    "type": "RECTANGLE",
    "id": "Rectangle 3",
    "pageNumber": null,
    "x": 0,
    "y": 842,
    "width": 842,
    "height": 595,
    "rotation": 90
  },
  {
    "type": "GROUP",
    "id": "Group 1",
    "pageNumber": null,
    "x": 581.135009765625,
    "y": -67.551025390625,
    "width": 193.1349639892578,
    "height": 139.64430236816406,
    "rotation": -180
  },
  {
    "type": "BOOLEAN_OPERATION",
    "id": "Intersect",
    "pageNumber": null,
    "x": 581.135009765625,
    "y": -67.551025390625,
    "width": 193.1349639892578,
    "height": 139.64430236816406,
    "rotation": -180
  },
  {
    "type": "BOOLEAN_OPERATION",
    "id": "Exclude",
    "pageNumber": null,
    "x": 581.1350095319684,
    "y": -67.551025390625,
    "width": 193.1349639892578,
    "height": 139.64430236816406,
    "rotation": -180
  },
  {
    "type": "VECTOR",
    "id": "Ellipse 2",
    "pageNumber": null,
    "x": 575.7223947095807,
    "y": -67.551025390625,
    "width": 187.72235107421875,
    "height": 138.4834747314453,
    "rotation": -180
  },
  {
    "type": "VECTOR",
    "id": "Ellipse 1",
    "pageNumber": null,
    "x": 581.1350095319684,
    "y": -65,
    "width": 192.13497924804688,
    "height": 137.09327697753906,
    "rotation": -180
  },
  {
    "type": "RECTANGLE",
    "id": "P06L04",
    "pageNumber": "6",
    "x": 57,
    "y": 426,
    "width": 480,
    "height": 322,
    "rotation": 0
  },
  {
    "type": "TEXT",
    "id": "P06L04",
    "rotation": 0,
    "textAlignment": {
      "horizontal": "JUSTIFIED",
      "vertical": "TOP"
    },
    "textProperties": {
      "fontName": "Urbanist",
      "fontSize": 17,
      "isBold": false
    },
    "color": [
      "#000000"
    ]
  },
  {
    "type": "RECTANGLE",
    "id": "P06L03",
    "pageNumber": "6",
    "x": 57,
    "y": 385,
    "width": 480,
    "height": 36,
    "rotation": 0
  },
  {
    "type": "TEXT",
    "id": "P06L03",
    "rotation": 0,
    "textAlignment": {
      "horizontal": "JUSTIFIED",
      "vertical": "CENTER"
    },
    "textProperties": {
      "fontName": "Urbanist",
      "fontSize": 18,
      "isBold": true
    },
    "color": [
      "#e90000"
    ]
  },
  {
    "type": "RECTANGLE",
    "id": "P06L02",
    "pageNumber": "6",
    "x": 57,
    "y": 147,
    "width": 480,
    "height": 209,
    "rotation": 0
  },
  {
    "type": "TEXT",
    "id": "P06L02",
    "rotation": 0,
    "textAlignment": {
      "horizontal": "JUSTIFIED",
      "vertical": "TOP"
    },
    "textProperties": {
      "fontName": "Urbanist",
      "fontSize": 17,
      "isBold": false
    },
    "color": [
      "#000000"
    ]
  },
  {
    "type": "RECTANGLE",
    "id": "P06L01",
    "pageNumber": "6",
    "x": 57,
    "y": 106,
    "width": 480,
    "height": 36,
    "rotation": 0
  },
  {
    "type": "TEXT",
    "id": "P06L01",
    "rotation": 0,
    "textAlignment": {
      "horizontal": "CENTER",
      "vertical": "CENTER"
    },
    "textProperties": {
      "fontName": "Urbanist",
      "fontSize": 18,
      "isBold": true
    },
    "color": [
      "#000000"
    ]
  },
  {
    "type": "RECTANGLE",
    "id": "P07L02",
    "pageNumber": "7",
    "x": 41,
    "y": 129,
    "width": 480,
    "height": 61,
    "rotation": 0
  },
  {
    "type": "TEXT",
    "id": "P07L02",
    "rotation": 0,
    "textAlignment": {
      "horizontal": "LEFT",
      "vertical": "CENTER"
    },
    "textProperties": {
      "fontName": "Urbanist",
      "fontSize": 18,
      "isBold": true
    },
    "color": [
      "#000000"
    ]
  },
  {
    "type": "RECTANGLE",
    "id": "P07L01",
    "pageNumber": "7",
    "x": 57,
    "y": 79,
    "width": 480,
    "height": 32,
    "rotation": 0
  },
  {
    "type": "TEXT",
    "id": "P07L01",
    "rotation": 0,
    "textAlignment": {
      "horizontal": "CENTER",
      "vertical": "CENTER"
    },
    "textProperties": {
      "fontName": "Urbanist",
      "fontSize": 18,
      "isBold": true
    },
    "color": [
      "#00c6c1"
    ]
  },
  {
    "type": "RECTANGLE",
    "id": "P08L06",
    "pageNumber": "8",
    "x": 41,
    "y": 603,
    "width": 518,
    "height": 203,
    "rotation": 0
  },
  {
    "type": "TEXT",
    "id": "P08L06",
    "rotation": 0,
    "textAlignment": {
      "horizontal": "JUSTIFIED",
      "vertical": "TOP"
    },
    "textProperties": {
      "fontName": "Urbanist",
      "fontSize": 17,
      "isBold": false
    },
    "color": [
      "#000000"
    ]
  },
  {
    "type": "RECTANGLE",
    "id": "P08L05",
    "pageNumber": "8",
    "x": 41,
    "y": 563,
    "width": 518,
    "height": 30,
    "rotation": 0
  },
  {
    "type": "TEXT",
    "id": "P08L05",
    "rotation": 0,
    "textAlignment": {
      "horizontal": "LEFT",
      "vertical": "CENTER"
    },
    "textProperties": {
      "fontName": "Urbanist",
      "fontSize": 18,
      "isBold": true
    },
    "color": [
      "#000000"
    ]
  },
  {
    "type": "RECTANGLE",
    "id": "P08L04",
    "pageNumber": "8",
    "x": 41,
    "y": 216,
    "width": 518,
    "height": 339,
    "rotation": 0
  },
  {
    "type": "TEXT",
    "id": "P08L04",
    "rotation": 0,
    "textAlignment": {
      "horizontal": "JUSTIFIED",
      "vertical": "TOP"
    },
    "textProperties": {
      "fontName": "Urbanist",
      "fontSize": 17,
      "isBold": false
    },
    "color": [
      "#000000"
    ]
  },
  {
    "type": "RECTANGLE",
    "id": "P08L03",
    "pageNumber": "8",
    "x": 41,
    "y": 175,
    "width": 518,
    "height": 29,
    "rotation": 0
  },
  {
    "type": "TEXT",
    "id": "P08L03",
    "rotation": 0,
    "textAlignment": {
      "horizontal": "LEFT",
      "vertical": "CENTER"
    },
    "textProperties": {
      "fontName": "Urbanist",
      "fontSize": 18,
      "isBold": true
    },
    "color": [
      "#000000"
    ]
  },
  {
    "type": "RECTANGLE",
    "id": "P08L02",
    "pageNumber": "8",
    "x": 213,
    "y": 101,
    "width": 341,
    "height": 48,
    "rotation": 0
  },
  {
    "type": "TEXT",
    "id": "P08L02",
    "rotation": 0,
    "textAlignment": {
      "horizontal": "JUSTIFIED",
      "vertical": "CENTER"
    },
    "textProperties": {
      "fontName": "Urbanist",
      "fontSize": 24,
      "isBold": true
    },
    "color": [
      "#ffffff"
    ]
  },
  {
    "type": "RECTANGLE",
    "id": "P08L01",
    "pageNumber": "8",
    "x": 89,
    "y": 105,
    "width": 112,
    "height": 38,
    "rotation": 0
  },
  {
    "type": "TEXT",
    "id": "P08L01",
    "rotation": 0,
    "textAlignment": {
      "horizontal": "LEFT",
      "vertical": "CENTER"
    },
    "textProperties": {
      "fontName": "Urbanist",
      "fontSize": 24,
      "isBold": true
    },
    "color": [
      "#e90000"
    ]
  },
  {
    "type": "RECTANGLE",
    "id": "P09L03",
    "pageNumber": "9",
    "x": 41,
    "y": 303,
    "width": 518,
    "height": 388,
    "rotation": 0
  },
  {
    "type": "TEXT",
    "id": "P09L03",
    "rotation": 0,
    "textAlignment": {
      "horizontal": "JUSTIFIED",
      "vertical": "TOP"
    },
    "textProperties": {
      "fontName": "Urbanist",
      "fontSize": 17,
      "isBold": false
    },
    "color": [
      "#000000"
    ]
  },
  {
    "type": "RECTANGLE",
    "id": "P09L02",
    "pageNumber": "9",
    "x": 41,
    "y": 258,
    "width": 518,
    "height": 34,
    "rotation": 0
  },
  {
    "type": "TEXT",
    "id": "P09L02",
    "rotation": 0,
    "textAlignment": {
      "horizontal": "JUSTIFIED",
      "vertical": "CENTER"
    },
    "textProperties": {
      "fontName": "Urbanist",
      "fontSize": 18,
      "isBold": true
    },
    "color": [
      "#000000"
    ]
  },
  {
    "type": "RECTANGLE",
    "id": "P09L01",
    "pageNumber": "9",
    "x": 41,
    "y": 74,
    "width": 518,
    "height": 164,
    "rotation": 0
  },
  {
    "type": "TEXT",
    "id": "P09L01",
    "rotation": 0,
    "textAlignment": {
      "horizontal": "JUSTIFIED",
      "vertical": "TOP"
    },
    "textProperties": {
      "fontName": "Urbanist",
      "fontSize": 17,
      "isBold": false
    },
    "color": [
      "#000000"
    ]
  },
  {
    "type": "RECTANGLE",
    "id": "P10L05",
    "pageNumber": "10",
    "x": 41,
    "y": 521,
    "width": 518,
    "height": 27,
    "rotation": 0
  },
  {
    "type": "TEXT",
    "id": "P10L05",
    "rotation": 0,
    "textAlignment": {
      "horizontal": "JUSTIFIED",
      "vertical": "CENTER"
    },
    "textProperties": {
      "fontName": "Urbanist",
      "fontSize": 18,
      "isBold": true
    },
    "color": [
      "#000000"
    ]
  },
  {
    "type": "RECTANGLE",
    "id": "P10L04",
    "pageNumber": "10",
    "x": 56,
    "y": 406,
    "width": 483,
    "height": 90,
    "rotation": 0
  },
  {
    "type": "TEXT",
    "id": "P10L04",
    "rotation": 0,
    "textAlignment": {
      "horizontal": "CENTER",
      "vertical": "CENTER"
    },
    "textProperties": {
      "fontName": "Urbanist",
      "fontSize": 17,
      "isBold": false
    },
    "color": [
      "#000000"
    ]
  },
  {
    "type": "RECTANGLE",
    "id": "P10L03",
    "pageNumber": "10",
    "x": 41,
    "y": 352,
    "width": 518,
    "height": 28,
    "rotation": 0
  },
  {
    "type": "TEXT",
    "id": "P10L03",
    "rotation": 0,
    "textAlignment": {
      "horizontal": "JUSTIFIED",
      "vertical": "CENTER"
    },
    "textProperties": {
      "fontName": "Urbanist",
      "fontSize": 18,
      "isBold": true
    },
    "color": [
      "#000000"
    ]
  },
  {
    "type": "RECTANGLE",
    "id": "P10L02",
    "pageNumber": "10",
    "x": 41,
    "y": 118,
    "width": 518,
    "height": 221,
    "rotation": 0
  },
  {
    "type": "TEXT",
    "id": "P10L02",
    "rotation": 0,
    "textAlignment": {
      "horizontal": "JUSTIFIED",
      "vertical": "CENTER"
    },
    "textProperties": {
      "fontName": "Urbanist",
      "fontSize": 17,
      "isBold": false
    },
    "color": [
      "#000000"
    ]
  },
  {
    "type": "RECTANGLE",
    "id": "P10L01",
    "pageNumber": "10",
    "x": 41,
    "y": 78,
    "width": 518,
    "height": 25,
    "rotation": 0
  },
  {
    "type": "TEXT",
    "id": "P10L01",
    "rotation": 0,
    "textAlignment": {
      "horizontal": "JUSTIFIED",
      "vertical": "CENTER"
    },
    "textProperties": {
      "fontName": "Urbanist",
      "fontSize": 18,
      "isBold": true
    },
    "color": [
      "#000000"
    ]
  },
  {
    "type": "RECTANGLE",
    "id": "P11L08",
    "pageNumber": "11",
    "x": 48,
    "y": 751,
    "width": 498,
    "height": 56,
    "rotation": 0
  },
  {
    "type": "TEXT",
    "id": "P11L08",
    "rotation": 0,
    "textAlignment": {
      "horizontal": "CENTER",
      "vertical": "CENTER"
    },
    "textProperties": {
      "fontName": "Urbanist",
      "fontSize": 17,
      "isBold": false
    },
    "color": [
      "#000000"
    ]
  },
  {
    "type": "RECTANGLE",
    "id": "P11L07",
    "pageNumber": "11",
    "x": 48,
    "y": 659,
    "width": 498,
    "height": 56,
    "rotation": 0
  },
  {
    "type": "TEXT",
    "id": "P11L07",
    "rotation": 0,
    "textAlignment": {
      "horizontal": "CENTER",
      "vertical": "TOP"
    },
    "textProperties": {
      "fontName": "Urbanist",
      "fontSize": 17,
      "isBold": false
    },
    "color": [
      "#ffffff"
    ]
  },
  {
    "type": "RECTANGLE",
    "id": "P11L06",
    "pageNumber": "11",
    "x": 48,
    "y": 606,
    "width": 498,
    "height": 51,
    "rotation": 0
  },
  {
    "type": "TEXT",
    "id": "P11L06",
    "rotation": 0,
    "textAlignment": {
      "horizontal": "CENTER",
      "vertical": "CENTER"
    },
    "textProperties": {
      "fontName": "Urbanist",
      "fontSize": 17,
      "isBold": true
    },
    "color": [
      "#ffffff"
    ]
  },
  {
    "type": "RECTANGLE",
    "id": "P11L05",
    "pageNumber": "11",
    "x": 48,
    "y": 430,
    "width": 498,
    "height": 118,
    "rotation": 0
  },
  {
    "type": "TEXT",
    "id": "P11L05",
    "rotation": 0,
    "textAlignment": {
      "horizontal": "CENTER",
      "vertical": "CENTER"
    },
    "textProperties": {
      "fontName": "Urbanist",
      "fontSize": 17,
      "isBold": false
    },
    "color": [
      "#000000"
    ]
  },
  {
    "type": "RECTANGLE",
    "id": "P11L04",
    "pageNumber": "11",
    "x": 48,
    "y": 377,
    "width": 498,
    "height": 51,
    "rotation": 0
  },
  {
    "type": "TEXT",
    "id": "P11L04",
    "rotation": 0,
    "textAlignment": {
      "horizontal": "CENTER",
      "vertical": "CENTER"
    },
    "textProperties": {
      "fontName": "Urbanist",
      "fontSize": 17,
      "isBold": true
    },
    "color": [
      "#000000"
    ]
  },
  {
    "type": "RECTANGLE",
    "id": "P11L03",
    "pageNumber": "11",
    "x": 48,
    "y": 227,
    "width": 498,
    "height": 86,
    "rotation": 0
  },
  {
    "type": "TEXT",
    "id": "P11L03",
    "rotation": 0,
    "textAlignment": {
      "horizontal": "CENTER",
      "vertical": "CENTER"
    },
    "textProperties": {
      "fontName": "Urbanist",
      "fontSize": 17,
      "isBold": false
    },
    "color": [
      "#ffffff"
    ]
  },
  {
    "type": "RECTANGLE",
    "id": "P11L02",
    "pageNumber": "11",
    "x": 48,
    "y": 157,
    "width": 498,
    "height": 51,
    "rotation": 0
  },
  {
    "type": "TEXT",
    "id": "P11L02",
    "rotation": 0,
    "textAlignment": {
      "horizontal": "CENTER",
      "vertical": "CENTER"
    },
    "textProperties": {
      "fontName": "Urbanist",
      "fontSize": 17,
      "isBold": true
    },
    "color": [
      "#ffffff"
    ]
  },
  {
    "type": "RECTANGLE",
    "id": "P11L01",
    "pageNumber": "11",
    "x": 41,
    "y": 88,
    "width": 518,
    "height": 27,
    "rotation": 0
  },
  {
    "type": "TEXT",
    "id": "P11L01",
    "rotation": 0,
    "textAlignment": {
      "horizontal": "JUSTIFIED",
      "vertical": "CENTER"
    },
    "textProperties": {
      "fontName": "Urbanist",
      "fontSize": 17,
      "isBold": false
    },
    "color": [
      "#000000"
    ]
  },
  {
    "type": "RECTANGLE",
    "id": "P12L04",
    "pageNumber": "12",
    "x": 41,
    "y": 216,
    "width": 518,
    "height": 579,
    "rotation": 0
  },
  {
    "type": "TEXT",
    "id": "P12L04",
    "rotation": 0,
    "textAlignment": {
      "horizontal": "JUSTIFIED",
      "vertical": "CENTER"
    },
    "textProperties": {
      "fontName": "Urbanist",
      "fontSize": 16,
      "isBold": false
    },
    "color": [
      "#000000"
    ]
  },
  {
    "type": "RECTANGLE",
    "id": "P12L03",
    "pageNumber": "12",
    "x": 41,
    "y": 175,
    "width": 518,
    "height": 29,
    "rotation": 0
  },
  {
    "type": "TEXT",
    "id": "P12L03",
    "rotation": 0,
    "textAlignment": {
      "horizontal": "JUSTIFIED",
      "vertical": "CENTER"
    },
    "textProperties": {
      "fontName": "Urbanist",
      "fontSize": 18,
      "isBold": true
    },
    "color": [
      "#000000"
    ]
  },
  {
    "type": "RECTANGLE",
    "id": "P12L02",
    "pageNumber": "12",
    "x": 213,
    "y": 101,
    "width": 341,
    "height": 48,
    "rotation": 0
  },
  {
    "type": "TEXT",
    "id": "P12L02",
    "rotation": 0,
    "textAlignment": {
      "horizontal": "JUSTIFIED",
      "vertical": "CENTER"
    },
    "textProperties": {
      "fontName": "Urbanist",
      "fontSize": 24,
      "isBold": true
    },
    "color": [
      "#ffffff"
    ]
  },
  {
    "type": "RECTANGLE",
    "id": "P12L01",
    "pageNumber": "12",
    "x": 89,
    "y": 105,
    "width": 112,
    "height": 38,
    "rotation": 0
  },
  {
    "type": "TEXT",
    "id": "P12L01",
    "rotation": 0,
    "textAlignment": {
      "horizontal": "JUSTIFIED",
      "vertical": "CENTER"
    },
    "textProperties": {
      "fontName": "Urbanist",
      "fontSize": 24,
      "isBold": true
    },
    "color": [
      "#e90000"
    ]
  },
  {
    "type": "RECTANGLE",
    "id": "P13L06",
    "pageNumber": "13",
    "x": 41,
    "y": 534,
    "width": 518,
    "height": 225,
    "rotation": 0
  },
  {
    "type": "TEXT",
    "id": "P13L06",
    "rotation": 0,
    "textAlignment": {
      "horizontal": "JUSTIFIED",
      "vertical": "TOP"
    },
    "textProperties": {
      "fontName": "Urbanist",
      "fontSize": 17,
      "isBold": false
    },
    "color": [
      "#000000"
    ]
  },
  {
    "type": "RECTANGLE",
    "id": "P13L05",
    "pageNumber": "13",
    "x": 41,
    "y": 481,
    "width": 518,
    "height": 29,
    "rotation": 0
  },
  {
    "type": "TEXT",
    "id": "P13L05",
    "rotation": 0,
    "textAlignment": {
      "horizontal": "JUSTIFIED",
      "vertical": "CENTER"
    },
    "textProperties": {
      "fontName": "Urbanist",
      "fontSize": 17,
      "isBold": true
    },
    "color": [
      "#e90000"
    ]
  },
  {
    "type": "RECTANGLE",
    "id": "P13L04",
    "pageNumber": "13",
    "x": 41,
    "y": 229,
    "width": 518,
    "height": 229,
    "rotation": 0
  },
  {
    "type": "TEXT",
    "id": "P13L04",
    "rotation": 0,
    "textAlignment": {
      "horizontal": "JUSTIFIED",
      "vertical": "TOP"
    },
    "textProperties": {
      "fontName": "Urbanist",
      "fontSize": 17,
      "isBold": false
    },
    "color": [
      "#000000"
    ]
  },
  {
    "type": "RECTANGLE",
    "id": "P13L03",
    "pageNumber": "13",
    "x": 41,
    "y": 181,
    "width": 518,
    "height": 29,
    "rotation": 0
  },
  {
    "type": "TEXT",
    "id": "P13L03",
    "rotation": 0,
    "textAlignment": {
      "horizontal": "JUSTIFIED",
      "vertical": "CENTER"
    },
    "textProperties": {
      "fontName": "Urbanist",
      "fontSize": 17,
      "isBold": true
    },
    "color": [
      "#e90000"
    ]
  },
  {
    "type": "RECTANGLE",
    "id": "P13L02",
    "pageNumber": "13",
    "x": 41,
    "y": 132,
    "width": 141,
    "height": 29,
    "rotation": 0
  },
  {
    "type": "TEXT",
    "id": "P13L02",
    "rotation": 0,
    "textAlignment": {
      "horizontal": "CENTER",
      "vertical": "CENTER"
    },
    "textProperties": {
      "fontName": "Urbanist",
      "fontSize": 18,
      "isBold": true
    },
    "color": [
      "#ffffff"
    ]
  },
  {
    "type": "RECTANGLE",
    "id": "P13L01",
    "pageNumber": "13",
    "x": 41,
    "y": 89,
    "width": 518,
    "height": 29,
    "rotation": 0
  },
  {
    "type": "TEXT",
    "id": "P13L01",
    "rotation": 0,
    "textAlignment": {
      "horizontal": "JUSTIFIED",
      "vertical": "CENTER"
    },
    "textProperties": {
      "fontName": "Urbanist",
      "fontSize": 18,
      "isBold": true
    },
    "color": [
      "#000000"
    ]
  },
  {
    "type": "RECTANGLE",
    "id": "P14L09",
    "pageNumber": "14",
    "x": 41,
    "y": 689,
    "width": 518,
    "height": 76,
    "rotation": 0
  },
  {
    "type": "TEXT",
    "id": "P14L09",
    "rotation": 0,
    "textAlignment": {
      "horizontal": "JUSTIFIED",
      "vertical": "TOP"
    },
    "textProperties": {
      "fontName": "Urbanist",
      "fontSize": 17,
      "isBold": false
    },
    "color": [
      "#000000"
    ]
  },
  {
    "type": "RECTANGLE",
    "id": "P14L08",
    "pageNumber": "14",
    "x": 41,
    "y": 644,
    "width": 518,
    "height": 29,
    "rotation": 0
  },
  {
    "type": "TEXT",
    "id": "P14L08",
    "rotation": 0,
    "textAlignment": {
      "horizontal": "JUSTIFIED",
      "vertical": "CENTER"
    },
    "textProperties": {
      "fontName": "Urbanist",
      "fontSize": 17,
      "isBold": true
    },
    "color": [
      "#e90000"
    ]
  },
  {
    "type": "RECTANGLE",
    "id": "P14L07",
    "pageNumber": "14",
    "x": 41,
    "y": 562,
    "width": 518,
    "height": 76,
    "rotation": 0
  },
  {
    "type": "TEXT",
    "id": "P14L07",
    "rotation": 0,
    "textAlignment": {
      "horizontal": "JUSTIFIED",
      "vertical": "TOP"
    },
    "textProperties": {
      "fontName": "Urbanist",
      "fontSize": 17,
      "isBold": false
    },
    "color": [
      "#000000"
    ]
  },
  {
    "type": "RECTANGLE",
    "id": "P14L06",
    "pageNumber": "14",
    "x": 41,
    "y": 514,
    "width": 518,
    "height": 29,
    "rotation": 0
  },
  {
    "type": "TEXT",
    "id": "P14L06",
    "rotation": 0,
    "textAlignment": {
      "horizontal": "JUSTIFIED",
      "vertical": "CENTER"
    },
    "textProperties": {
      "fontName": "Urbanist",
      "fontSize": 17,
      "isBold": true
    },
    "color": [
      "#e90000"
    ]
  },
  {
    "type": "RECTANGLE",
    "id": "P14L05",
    "pageNumber": "14",
    "x": 41,
    "y": 415,
    "width": 518,
    "height": 95,
    "rotation": 0
  },
  {
    "type": "TEXT",
    "id": "P14L05",
    "rotation": 0,
    "textAlignment": {
      "horizontal": "JUSTIFIED",
      "vertical": "TOP"
    },
    "textProperties": {
      "fontName": "Urbanist",
      "fontSize": 17,
      "isBold": false
    },
    "color": [
      "#000000"
    ]
  },
  {
    "type": "RECTANGLE",
    "id": "P14L04",
    "pageNumber": "14",
    "x": 41,
    "y": 367,
    "width": 518,
    "height": 29,
    "rotation": 0
  },
  {
    "type": "TEXT",
    "id": "P14L04",
    "rotation": 0,
    "textAlignment": {
      "horizontal": "JUSTIFIED",
      "vertical": "CENTER"
    },
    "textProperties": {
      "fontName": "Urbanist",
      "fontSize": 17,
      "isBold": true
    },
    "color": [
      "#e90000"
    ]
  },
  {
    "type": "RECTANGLE",
    "id": "P14L03",
    "pageNumber": "14",
    "x": 41,
    "y": 186,
    "width": 518,
    "height": 174,
    "rotation": 0
  },
  {
    "type": "TEXT",
    "id": "P14L03",
    "rotation": 0,
    "textAlignment": {
      "horizontal": "JUSTIFIED",
      "vertical": "TOP"
    },
    "textProperties": {
      "fontName": "Urbanist",
      "fontSize": 17,
      "isBold": false
    },
    "color": [
      "#000000"
    ]
  },
  {
    "type": "RECTANGLE",
    "id": "P14L02",
    "pageNumber": "14",
    "x": 41,
    "y": 138,
    "width": 518,
    "height": 29,
    "rotation": 0
  },
  {
    "type": "TEXT",
    "id": "P14L02",
    "rotation": 0,
    "textAlignment": {
      "horizontal": "JUSTIFIED",
      "vertical": "CENTER"
    },
    "textProperties": {
      "fontName": "Urbanist",
      "fontSize": 17,
      "isBold": true
    },
    "color": [
      "#e90000"
    ]
  },
  {
    "type": "RECTANGLE",
    "id": "P14L01",
    "pageNumber": "14",
    "x": 41,
    "y": 92,
    "width": 141,
    "height": 29,
    "rotation": 0
  },
  {
    "type": "TEXT",
    "id": "P14L01",
    "rotation": 0,
    "textAlignment": {
      "horizontal": "CENTER",
      "vertical": "CENTER"
    },
    "textProperties": {
      "fontName": "Urbanist",
      "fontSize": 18,
      "isBold": true
    },
    "color": [
      "#ffffff"
    ]
  },
  {
    "type": "RECTANGLE",
    "id": "P15L02",
    "pageNumber": "15",
    "x": 41,
    "y": 140,
    "width": 518,
    "height": 29,
    "rotation": 0
  },
  {
    "type": "TEXT",
    "id": "P15L02",
    "rotation": 0,
    "textAlignment": {
      "horizontal": "LEFT",
      "vertical": "CENTER"
    },
    "textProperties": {
      "fontName": "Urbanist",
      "fontSize": 24,
      "isBold": true
    },
    "color": [
      "#00c6c1"
    ]
  },
  {
    "type": "RECTANGLE",
    "id": "P15L01",
    "pageNumber": "15",
    "x": 41,
    "y": 92,
    "width": 141,
    "height": 29,
    "rotation": 0
  },
  {
    "type": "TEXT",
    "id": "P15L01",
    "rotation": 0,
    "textAlignment": {
      "horizontal": "CENTER",
      "vertical": "TOP"
    },
    "textProperties": {
      "fontName": "Urbanist",
      "fontSize": 18,
      "isBold": true
    },
    "color": [
      "#ffffff"
    ]
  },
  {
    "type": "INSTANCE",
    "id": "tag",
    "pageNumber": "15",
    "x": 40,
    "y": 91,
    "width": 142,
    "height": 31,
    "rotation": 0
  },
  {
    "type": "TEXT",
    "id": "Avant l’atelier",
    "rotation": 0,
    "textAlignment": {
      "horizontal": "CENTER",
      "vertical": "CENTER"
    },
    "textProperties": {
      "fontName": "Urbanist",
      "fontSize": 18,
      "isBold": true
    },
    "color": [
      "#ffffff"
    ]
  },
  {
    "type": "RECTANGLE",
    "id": "P16L06",
    "pageNumber": "16",
    "x": 38,
    "y": 693,
    "width": 297,
    "height": 114,
    "rotation": 0
  },
  {
    "type": "TEXT",
    "id": "P16L06",
    "rotation": 0,
    "textAlignment": {
      "horizontal": "LEFT",
      "vertical": "CENTER"
    },
    "textProperties": {
      "fontName": "Urbanist",
      "fontSize": 17,
      "isBold": false
    },
    "color": [
      "#007580"
    ]
  },
  {
    "type": "RECTANGLE",
    "id": "P16L05",
    "pageNumber": "16",
    "x": 268,
    "y": 534,
    "width": 297,
    "height": 133,
    "rotation": 0
  },
  {
    "type": "TEXT",
    "id": "P16L05",
    "rotation": 0,
    "textAlignment": {
      "horizontal": "LEFT",
      "vertical": "CENTER"
    },
    "textProperties": {
      "fontName": "Urbanist",
      "fontSize": 17,
      "isBold": false
    },
    "color": [
      "#007580"
    ]
  },
  {
    "type": "RECTANGLE",
    "id": "P16L04",
    "pageNumber": "16",
    "x": 38,
    "y": 368,
    "width": 297,
    "height": 147,
    "rotation": 0
  },
  {
    "type": "TEXT",
    "id": "P16L04",
    "rotation": 0,
    "textAlignment": {
      "horizontal": "LEFT",
      "vertical": "CENTER"
    },
    "textProperties": {
      "fontName": "Urbanist",
      "fontSize": 17,
      "isBold": false
    },
    "color": [
      "#007580"
    ]
  },
  {
    "type": "RECTANGLE",
    "id": "P16L03",
    "pageNumber": "16",
    "x": 268,
    "y": 222,
    "width": 297,
    "height": 133,
    "rotation": 0
  },
  {
    "type": "TEXT",
    "id": "P16L03",
    "rotation": 0,
    "textAlignment": {
      "horizontal": "LEFT",
      "vertical": "CENTER"
    },
    "textProperties": {
      "fontName": "Urbanist",
      "fontSize": 17,
      "isBold": false
    },
    "color": [
      "#007580"
    ]
  },
  {
    "type": "RECTANGLE",
    "id": "P16L02",
    "pageNumber": "16",
    "x": 70,
    "y": 142,
    "width": 449,
    "height": 62,
    "rotation": 0
  },
  {
    "type": "TEXT",
    "id": "P16L02",
    "rotation": 0,
    "textAlignment": {
      "horizontal": "CENTER",
      "vertical": "CENTER"
    },
    "textProperties": {
      "fontName": "Urbanist",
      "fontSize": 24,
      "isBold": true
    },
    "color": [
      "#007580"
    ]
  },
  {
    "type": "RECTANGLE",
    "id": "P16L01",
    "pageNumber": "16",
    "x": 41,
    "y": 92,
    "width": 141,
    "height": 29,
    "rotation": 0
  },
  {
    "type": "TEXT",
    "id": "P16L01",
    "rotation": 0,
    "textAlignment": {
      "horizontal": "CENTER",
      "vertical": "CENTER"
    },
    "textProperties": {
      "fontName": "Urbanist",
      "fontSize": 18,
      "isBold": true
    },
    "color": [
      "#ffffff"
    ]
  },
  {
    "type": "RECTANGLE",
    "id": "P29L01",
    "pageNumber": "29",
    "x": 41,
    "y": 85,
    "width": 518,
    "height": 33,
    "rotation": 0
  },
  {
    "type": "TEXT",
    "id": "P29L01",
    "rotation": 0,
    "textAlignment": {
      "horizontal": "LEFT",
      "vertical": "CENTER"
    },
    "textProperties": {
      "fontName": "Urbanist",
      "fontSize": 18,
      "isBold": true
    },
    "color": [
      "#e90000"
    ]
  },
  {
    "type": "RECTANGLE",
    "id": "P30L01",
    "pageNumber": "30",
    "x": 41,
    "y": 85,
    "width": 518,
    "height": 33,
    "rotation": 0
  },
  {
    "type": "TEXT",
    "id": "P30L01",
    "rotation": 0,
    "textAlignment": {
      "horizontal": "LEFT",
      "vertical": "CENTER"
    },
    "textProperties": {
      "fontName": "Urbanist",
      "fontSize": 18,
      "isBold": true
    },
    "color": [
      "#e90000"
    ]
  },
  {
    "type": "RECTANGLE",
    "id": "P17L07",
    "pageNumber": "17",
    "x": 41,
    "y": 485,
    "width": 518,
    "height": 312,
    "rotation": 0
  },
  {
    "type": "TEXT",
    "id": "P17L07",
    "rotation": 0,
    "textAlignment": {
      "horizontal": "JUSTIFIED",
      "vertical": "TOP"
    },
    "textProperties": {
      "fontName": "Urbanist",
      "fontSize": 17,
      "isBold": false
    },
    "color": [
      "#000000"
    ]
  },
  {
    "type": "RECTANGLE",
    "id": "P17L06",
    "pageNumber": "17",
    "x": 41,
    "y": 444,
    "width": 518,
    "height": 29,
    "rotation": 0
  },
  {
    "type": "TEXT",
    "id": "P17L06",
    "rotation": 0,
    "textAlignment": {
      "horizontal": "JUSTIFIED",
      "vertical": "CENTER"
    },
    "textProperties": {
      "fontName": "Urbanist",
      "fontSize": 18,
      "isBold": true
    },
    "color": [
      "#000000"
    ]
  },
  {
    "type": "RECTANGLE",
    "id": "P17L05",
    "pageNumber": "17",
    "x": 41,
    "y": 293,
    "width": 518,
    "height": 139,
    "rotation": 0
  },
  {
    "type": "TEXT",
    "id": "P17L05",
    "rotation": 0,
    "textAlignment": {
      "horizontal": "JUSTIFIED",
      "vertical": "TOP"
    },
    "textProperties": {
      "fontName": "Urbanist",
      "fontSize": 17,
      "isBold": false
    },
    "color": [
      "#000000"
    ]
  },
  {
    "type": "RECTANGLE",
    "id": "P17L04",
    "pageNumber": "17",
    "x": 41,
    "y": 253,
    "width": 518,
    "height": 29,
    "rotation": 0
  },
  {
    "type": "TEXT",
    "id": "P17L04",
    "rotation": 0,
    "textAlignment": {
      "horizontal": "JUSTIFIED",
      "vertical": "CENTER"
    },
    "textProperties": {
      "fontName": "Urbanist",
      "fontSize": 18,
      "isBold": true
    },
    "color": [
      "#000000"
    ]
  },
  {
    "type": "RECTANGLE",
    "id": "P17L03",
    "pageNumber": "17",
    "x": 41,
    "y": 171,
    "width": 518,
    "height": 74,
    "rotation": 0
  },
  {
    "type": "TEXT",
    "id": "P17L03",
    "rotation": 0,
    "textAlignment": {
      "horizontal": "JUSTIFIED",
      "vertical": "TOP"
    },
    "textProperties": {
      "fontName": "Urbanist",
      "fontSize": 17,
      "isBold": false
    },
    "color": [
      "#000000"
    ]
  },
  {
    "type": "RECTANGLE",
    "id": "P17L02",
    "pageNumber": "17",
    "x": 41,
    "y": 135,
    "width": 518,
    "height": 29,
    "rotation": 0
  },
  {
    "type": "TEXT",
    "id": "P17L02",
    "rotation": 0,
    "textAlignment": {
      "horizontal": "JUSTIFIED",
      "vertical": "CENTER"
    },
    "textProperties": {
      "fontName": "Urbanist",
      "fontSize": 17,
      "isBold": true
    },
    "color": [
      "#e90000"
    ]
  },
  {
    "type": "RECTANGLE",
    "id": "P17L01",
    "pageNumber": "17",
    "x": 41,
    "y": 92,
    "width": 141,
    "height": 29,
    "rotation": 0
  },
  {
    "type": "TEXT",
    "id": "P17L01",
    "rotation": 0,
    "textAlignment": {
      "horizontal": "CENTER",
      "vertical": "CENTER"
    },
    "textProperties": {
      "fontName": "Urbanist",
      "fontSize": 18,
      "isBold": true
    },
    "color": [
      "#ffffff"
    ]
  },
  {
    "type": "RECTANGLE",
    "id": "P18L04",
    "pageNumber": "18",
    "x": 41,
    "y": 276,
    "width": 518,
    "height": 32,
    "rotation": 0
  },
  {
    "type": "TEXT",
    "id": "P18L04",
    "rotation": 0,
    "textAlignment": {
      "horizontal": "JUSTIFIED",
      "vertical": "CENTER"
    },
    "textProperties": {
      "fontName": "Urbanist",
      "fontSize": 18,
      "isBold": true
    },
    "color": [
      "#000000"
    ]
  },
  {
    "type": "RECTANGLE",
    "id": "P18L03",
    "pageNumber": "18",
    "x": 41,
    "y": 176,
    "width": 518,
    "height": 92,
    "rotation": 0
  },
  {
    "type": "TEXT",
    "id": "P18L03",
    "rotation": 0,
    "textAlignment": {
      "horizontal": "JUSTIFIED",
      "vertical": "TOP"
    },
    "textProperties": {
      "fontName": "Urbanist",
      "fontSize": 17,
      "isBold": false
    },
    "color": [
      "#000000"
    ]
  },
  {
    "type": "RECTANGLE",
    "id": "P18L02",
    "pageNumber": "18",
    "x": 213,
    "y": 101,
    "width": 341,
    "height": 48,
    "rotation": 0
  },
  {
    "type": "TEXT",
    "id": "P18L02",
    "rotation": 0,
    "textAlignment": {
      "horizontal": "JUSTIFIED",
      "vertical": "CENTER"
    },
    "textProperties": {
      "fontName": "Urbanist",
      "fontSize": 24,
      "isBold": true
    },
    "color": [
      "#ffffff"
    ]
  },
  {
    "type": "RECTANGLE",
    "id": "P18L01",
    "pageNumber": "18",
    "x": 89,
    "y": 105,
    "width": 112,
    "height": 38,
    "rotation": 0
  },
  {
    "type": "TEXT",
    "id": "P18L01",
    "rotation": 0,
    "textAlignment": {
      "horizontal": "JUSTIFIED",
      "vertical": "CENTER"
    },
    "textProperties": {
      "fontName": "Urbanist",
      "fontSize": 24,
      "isBold": true
    },
    "color": [
      "#e90000"
    ]
  },
  {
    "type": "RECTANGLE",
    "id": "P21L13",
    "pageNumber": "21",
    "x": 144,
    "y": 727,
    "width": 404,
    "height": 72,
    "rotation": 0
  },
  {
    "type": "TEXT",
    "id": "P21L13",
    "rotation": 0,
    "textAlignment": {
      "horizontal": "JUSTIFIED",
      "vertical": "TOP"
    },
    "textProperties": {
      "fontName": "Urbanist",
      "fontSize": 14,
      "isBold": false
    },
    "color": [
      "#000000"
    ]
  },
  {
    "type": "RECTANGLE",
    "id": "P21L12",
    "pageNumber": "21",
    "x": 144,
    "y": 696,
    "width": 404,
    "height": 28,
    "rotation": 0
  },
  {
    "type": "TEXT",
    "id": "P21L12",
    "rotation": 0,
    "textAlignment": {
      "horizontal": "JUSTIFIED",
      "vertical": "CENTER"
    },
    "textProperties": {
      "fontName": "Urbanist",
      "fontSize": 18,
      "isBold": true
    },
    "color": [
      "#000000"
    ]
  },
  {
    "type": "RECTANGLE",
    "id": "P21L11",
    "pageNumber": "21",
    "x": 144,
    "y": 630,
    "width": 404,
    "height": 61,
    "rotation": 0
  },
  {
    "type": "TEXT",
    "id": "P21L11",
    "rotation": 0,
    "textAlignment": {
      "horizontal": "JUSTIFIED",
      "vertical": "TOP"
    },
    "textProperties": {
      "fontName": "Urbanist",
      "fontSize": 14,
      "isBold": false
    },
    "color": [
      "#000000"
    ]
  },
  {
    "type": "RECTANGLE",
    "id": "P21L10",
    "pageNumber": "21",
    "x": 144,
    "y": 599,
    "width": 404,
    "height": 28,
    "rotation": 0
  },
  {
    "type": "TEXT",
    "id": "P21L10",
    "rotation": 0,
    "textAlignment": {
      "horizontal": "JUSTIFIED",
      "vertical": "CENTER"
    },
    "textProperties": {
      "fontName": "Urbanist",
      "fontSize": 18,
      "isBold": true
    },
    "color": [
      "#000000"
    ]
  },
  {
    "type": "RECTANGLE",
    "id": "P21L09",
    "pageNumber": "21",
    "x": 144,
    "y": 485,
    "width": 404,
    "height": 113,
    "rotation": 0
  },
  {
    "type": "TEXT",
    "id": "P21L09",
    "rotation": 0,
    "textAlignment": {
      "horizontal": "JUSTIFIED",
      "vertical": "TOP"
    },
    "textProperties": {
      "fontName": "Urbanist",
      "fontSize": 14,
      "isBold": false
    },
    "color": [
      "#000000"
    ]
  },
  {
    "type": "RECTANGLE",
    "id": "P21L08",
    "pageNumber": "21",
    "x": 144,
    "y": 454,
    "width": 404,
    "height": 28,
    "rotation": 0
  },
  {
    "type": "TEXT",
    "id": "P21L08",
    "rotation": 0,
    "textAlignment": {
      "horizontal": "JUSTIFIED",
      "vertical": "CENTER"
    },
    "textProperties": {
      "fontName": "Urbanist",
      "fontSize": 18,
      "isBold": true
    },
    "color": [
      "#000000"
    ]
  },
  {
    "type": "RECTANGLE",
    "id": "P21L07",
    "pageNumber": "21",
    "x": 144,
    "y": 390,
    "width": 404,
    "height": 57,
    "rotation": 0
  },
  {
    "type": "TEXT",
    "id": "P21L07",
    "rotation": 0,
    "textAlignment": {
      "horizontal": "JUSTIFIED",
      "vertical": "TOP"
    },
    "textProperties": {
      "fontName": "Urbanist",
      "fontSize": 14,
      "isBold": false
    },
    "color": [
      "#000000"
    ]
  },
  {
    "type": "RECTANGLE",
    "id": "P21L06",
    "pageNumber": "21",
    "x": 144,
    "y": 359,
    "width": 404,
    "height": 28,
    "rotation": 0
  },
  {
    "type": "TEXT",
    "id": "P21L06",
    "rotation": 0,
    "textAlignment": {
      "horizontal": "JUSTIFIED",
      "vertical": "CENTER"
    },
    "textProperties": {
      "fontName": "Urbanist",
      "fontSize": 18,
      "isBold": true
    },
    "color": [
      "#000000"
    ]
  },
  {
    "type": "RECTANGLE",
    "id": "P21L05",
    "pageNumber": "21",
    "x": 144,
    "y": 297,
    "width": 404,
    "height": 57,
    "rotation": 0
  },
  {
    "type": "TEXT",
    "id": "P21L05",
    "rotation": 0,
    "textAlignment": {
      "horizontal": "JUSTIFIED",
      "vertical": "TOP"
    },
    "textProperties": {
      "fontName": "Urbanist",
      "fontSize": 14,
      "isBold": false
    },
    "color": [
      "#000000"
    ]
  },
  {
    "type": "RECTANGLE",
    "id": "P21L04",
    "pageNumber": "21",
    "x": 144,
    "y": 266,
    "width": 404,
    "height": 28,
    "rotation": 0
  },
  {
    "type": "TEXT",
    "id": "P21L04",
    "rotation": 0,
    "textAlignment": {
      "horizontal": "JUSTIFIED",
      "vertical": "CENTER"
    },
    "textProperties": {
      "fontName": "Urbanist",
      "fontSize": 18,
      "isBold": true
    },
    "color": [
      "#000000"
    ]
  },
  {
    "type": "RECTANGLE",
    "id": "P21L03",
    "pageNumber": "21",
    "x": 41,
    "y": 172,
    "width": 518,
    "height": 58,
    "rotation": 0
  },
  {
    "type": "TEXT",
    "id": "P21L03",
    "rotation": 0,
    "textAlignment": {
      "horizontal": "JUSTIFIED",
      "vertical": "CENTER"
    },
    "textProperties": {
      "fontName": "Urbanist",
      "fontSize": 18,
      "isBold": true
    },
    "color": [
      "#000000"
    ]
  },
  {
    "type": "RECTANGLE",
    "id": "P21L02",
    "pageNumber": "21",
    "x": 213,
    "y": 101,
    "width": 341,
    "height": 48,
    "rotation": 0
  },
  {
    "type": "TEXT",
    "id": "P21L02",
    "rotation": 0,
    "textAlignment": {
      "horizontal": "JUSTIFIED",
      "vertical": "CENTER"
    },
    "textProperties": {
      "fontName": "Urbanist",
      "fontSize": 24,
      "isBold": true
    },
    "color": [
      "#ffffff"
    ]
  },
  {
    "type": "RECTANGLE",
    "id": "P21L01",
    "pageNumber": "21",
    "x": 89,
    "y": 105,
    "width": 112,
    "height": 38,
    "rotation": 0
  },
  {
    "type": "TEXT",
    "id": "P21L01",
    "rotation": 0,
    "textAlignment": {
      "horizontal": "JUSTIFIED",
      "vertical": "CENTER"
    },
    "textProperties": {
      "fontName": "Urbanist",
      "fontSize": 24,
      "isBold": true
    },
    "color": [
      "#e90000"
    ]
  },
  {
    "type": "INSTANCE",
    "id": "red header",
    "pageNumber": "21",
    "x": 24,
    "y": 91,
    "width": 546,
    "height": 68,
    "rotation": 0
  },
  {
    "type": "RECTANGLE",
    "id": "logo 1",
    "pageNumber": null,
    "x": 0,
    "y": 0,
    "width": 68,
    "height": 68,
    "rotation": 0
  },
  {
    "type": "VECTOR",
    "id": "Rectangle 19",
    "pageNumber": null,
    "x": 187,
    "y": 7,
    "width": 359,
    "height": 58,
    "rotation": 0
  },
  {
    "type": "RECTANGLE",
    "id": "Rectangle 18",
    "pageNumber": null,
    "x": 20,
    "y": 7,
    "width": 167,
    "height": 58,
    "rotation": 0
  },
  {
    "type": "RECTANGLE",
    "id": "P22L06",
    "pageNumber": "22",
    "x": 41,
    "y": 688,
    "width": 518,
    "height": 117,
    "rotation": 0
  },
  {
    "type": "TEXT",
    "id": "P22L06",
    "rotation": 0,
    "textAlignment": {
      "horizontal": "JUSTIFIED",
      "vertical": "TOP"
    },
    "textProperties": {
      "fontName": "Urbanist",
      "fontSize": 17,
      "isBold": false
    },
    "color": [
      "#000000"
    ]
  },
  {
    "type": "RECTANGLE",
    "id": "P22L05",
    "pageNumber": "22",
    "x": 41,
    "y": 636,
    "width": 518,
    "height": 47,
    "rotation": 0
  },
  {
    "type": "TEXT",
    "id": "P22L05",
    "rotation": 0,
    "textAlignment": {
      "horizontal": "JUSTIFIED",
      "vertical": "CENTER"
    },
    "textProperties": {
      "fontName": "Urbanist",
      "fontSize": 17,
      "isBold": true
    },
    "color": [
      "#000000"
    ]
  },
  {
    "type": "RECTANGLE",
    "id": "P22L04",
    "pageNumber": "22",
    "x": 41,
    "y": 536,
    "width": 518,
    "height": 90,
    "rotation": 0
  },
  {
    "type": "TEXT",
    "id": "P22L04",
    "rotation": 0,
    "textAlignment": {
      "horizontal": "JUSTIFIED",
      "vertical": "TOP"
    },
    "textProperties": {
      "fontName": "Urbanist",
      "fontSize": 17,
      "isBold": false
    },
    "color": [
      "#000000"
    ]
  },
  {
    "type": "RECTANGLE",
    "id": "P22L03",
    "pageNumber": "22",
    "x": 41,
    "y": 472,
    "width": 518,
    "height": 58,
    "rotation": 0
  },
  {
    "type": "TEXT",
    "id": "P22L03",
    "rotation": 0,
    "textAlignment": {
      "horizontal": "JUSTIFIED",
      "vertical": "CENTER"
    },
    "textProperties": {
      "fontName": "Urbanist",
      "fontSize": 18,
      "isBold": true
    },
    "color": [
      "#000000"
    ]
  },
  {
    "type": "RECTANGLE",
    "id": "P22L02",
    "pageNumber": "22",
    "x": 213,
    "y": 101,
    "width": 341,
    "height": 48,
    "rotation": 0
  },
  {
    "type": "TEXT",
    "id": "P22L02",
    "rotation": 0,
    "textAlignment": {
      "horizontal": "JUSTIFIED",
      "vertical": "CENTER"
    },
    "textProperties": {
      "fontName": "Urbanist",
      "fontSize": 24,
      "isBold": true
    },
    "color": [
      "#ffffff"
    ]
  },
  {
    "type": "RECTANGLE",
    "id": "P22L01",
    "pageNumber": "22",
    "x": 89,
    "y": 105,
    "width": 112,
    "height": 38,
    "rotation": 0
  },
  {
    "type": "TEXT",
    "id": "P22L01",
    "rotation": 0,
    "textAlignment": {
      "horizontal": "JUSTIFIED",
      "vertical": "CENTER"
    },
    "textProperties": {
      "fontName": "Urbanist",
      "fontSize": 24,
      "isBold": true
    },
    "color": [
      "#e90000"
    ]
  },
  {
    "type": "RECTANGLE",
    "id": "P25L05",
    "pageNumber": "25",
    "x": 41,
    "y": 310,
    "width": 518,
    "height": 474,
    "rotation": 0
  },
  {
    "type": "TEXT",
    "id": "P25L05",
    "rotation": 0,
    "textAlignment": {
      "horizontal": "JUSTIFIED",
      "vertical": "CENTER"
    },
    "textProperties": {
      "fontName": "Urbanist",
      "fontSize": 17,
      "isBold": false
    },
    "color": [
      "#000000"
    ]
  },
  {
    "type": "RECTANGLE",
    "id": "P25L04",
    "pageNumber": "25",
    "x": 41,
    "y": 271,
    "width": 518,
    "height": 33,
    "rotation": 0
  },
  {
    "type": "TEXT",
    "id": "P25L04",
    "rotation": 0,
    "textAlignment": {
      "horizontal": "JUSTIFIED",
      "vertical": "CENTER"
    },
    "textProperties": {
      "fontName": "Urbanist",
      "fontSize": 18,
      "isBold": true
    },
    "color": [
      "#000000"
    ]
  },
  {
    "type": "RECTANGLE",
    "id": "P25L03",
    "pageNumber": "25",
    "x": 41,
    "y": 172,
    "width": 518,
    "height": 91,
    "rotation": 0
  },
  {
    "type": "TEXT",
    "id": "P25L03",
    "rotation": 0,
    "textAlignment": {
      "horizontal": "JUSTIFIED",
      "vertical": "CENTER"
    },
    "textProperties": {
      "fontName": "Urbanist",
      "fontSize": 17,
      "isBold": false
    },
    "color": [
      "#000000"
    ]
  },
  {
    "type": "RECTANGLE",
    "id": "P25L02",
    "pageNumber": "25",
    "x": 213,
    "y": 101,
    "width": 341,
    "height": 48,
    "rotation": 0
  },
  {
    "type": "TEXT",
    "id": "P25L02",
    "rotation": 0,
    "textAlignment": {
      "horizontal": "JUSTIFIED",
      "vertical": "CENTER"
    },
    "textProperties": {
      "fontName": "Urbanist",
      "fontSize": 24,
      "isBold": true
    },
    "color": [
      "#ffffff"
    ]
  },
  {
    "type": "RECTANGLE",
    "id": "P25L01",
    "pageNumber": "25",
    "x": 89,
    "y": 105,
    "width": 112,
    "height": 38,
    "rotation": 0
  },
  {
    "type": "TEXT",
    "id": "P25L01",
    "rotation": 0,
    "textAlignment": {
      "horizontal": "JUSTIFIED",
      "vertical": "CENTER"
    },
    "textProperties": {
      "fontName": "Urbanist",
      "fontSize": 24,
      "isBold": true
    },
    "color": [
      "#e90000"
    ]
  },
  {
    "type": "RECTANGLE",
    "id": "P27L04",
    "pageNumber": "27",
    "x": 41,
    "y": 478,
    "width": 518,
    "height": 277,
    "rotation": 0
  },
  {
    "type": "TEXT",
    "id": "P27L04",
    "rotation": 0,
    "textAlignment": {
      "horizontal": "JUSTIFIED",
      "vertical": "TOP"
    },
    "textProperties": {
      "fontName": "Urbanist",
      "fontSize": 17,
      "isBold": false
    },
    "color": [
      "#000000"
    ]
  },
  {
    "type": "RECTANGLE",
    "id": "P27L03",
    "pageNumber": "27",
    "x": 41,
    "y": 425,
    "width": 518,
    "height": 43,
    "rotation": 0
  },
  {
    "type": "TEXT",
    "id": "P27L03",
    "rotation": 0,
    "textAlignment": {
      "horizontal": "JUSTIFIED",
      "vertical": "CENTER"
    },
    "textProperties": {
      "fontName": "Urbanist",
      "fontSize": 18,
      "isBold": true
    },
    "color": [
      "#000000"
    ]
  },
  {
    "type": "RECTANGLE",
    "id": "P27L02",
    "pageNumber": "27",
    "x": 41,
    "y": 124,
    "width": 518,
    "height": 277,
    "rotation": 0
  },
  {
    "type": "TEXT",
    "id": "P27L02",
    "rotation": 0,
    "textAlignment": {
      "horizontal": "JUSTIFIED",
      "vertical": "TOP"
    },
    "textProperties": {
      "fontName": "Urbanist",
      "fontSize": 17,
      "isBold": false
    },
    "color": [
      "#000000"
    ]
  },
  {
    "type": "RECTANGLE",
    "id": "P27L01",
    "pageNumber": "27",
    "x": 41,
    "y": 85,
    "width": 518,
    "height": 33,
    "rotation": 0
  },
  {
    "type": "TEXT",
    "id": "P27L01",
    "rotation": 0,
    "textAlignment": {
      "horizontal": "JUSTIFIED",
      "vertical": "CENTER"
    },
    "textProperties": {
      "fontName": "Urbanist",
      "fontSize": 18,
      "isBold": true
    },
    "color": [
      "#000000"
    ]
  },
  {
    "type": "RECTANGLE",
    "id": "P28L02",
    "pageNumber": "28",
    "x": 41,
    "y": 130,
    "width": 518,
    "height": 277,
    "rotation": 0
  },
  {
    "type": "TEXT",
    "id": "P28L02",
    "rotation": 0,
    "textAlignment": {
      "horizontal": "JUSTIFIED",
      "vertical": "TOP"
    },
    "textProperties": {
      "fontName": "Urbanist",
      "fontSize": 17,
      "isBold": false
    },
    "color": [
      "#000000"
    ]
  },
  {
    "type": "RECTANGLE",
    "id": "P28L01",
    "pageNumber": "28",
    "x": 41,
    "y": 85,
    "width": 518,
    "height": 33,
    "rotation": 0
  },
  {
    "type": "TEXT",
    "id": "P28L01",
    "rotation": 0,
    "textAlignment": {
      "horizontal": "JUSTIFIED",
      "vertical": "CENTER"
    },
    "textProperties": {
      "fontName": "Urbanist",
      "fontSize": 18,
      "isBold": true
    },
    "color": [
      "#000000"
    ]
  },
  {
    "type": "RECTANGLE",
    "id": "P26L01",
    "pageNumber": "26",
    "x": 41,
    "y": 87,
    "width": 518,
    "height": 38,
    "rotation": 0
  },
  {
    "type": "TEXT",
    "id": "P26L01",
    "rotation": 0,
    "textAlignment": {
      "horizontal": "JUSTIFIED",
      "vertical": "CENTER"
    },
    "textProperties": {
      "fontName": "Urbanist",
      "fontSize": 24,
      "isBold": true
    },
    "color": [
      "#007580"
    ]
  },
  {
    "type": "RECTANGLE",
    "id": "P23L03",
    "pageNumber": "23",
    "x": 41,
    "y": 432,
    "width": 518,
    "height": 170,
    "rotation": 0
  },
  {
    "type": "TEXT",
    "id": "P23L03",
    "rotation": 0,
    "textAlignment": {
      "horizontal": "JUSTIFIED",
      "vertical": "TOP"
    },
    "textProperties": {
      "fontName": "Urbanist",
      "fontSize": 17,
      "isBold": false
    },
    "color": [
      "#000000"
    ]
  },
  {
    "type": "RECTANGLE",
    "id": "P23L02",
    "pageNumber": "23",
    "x": 41,
    "y": 382,
    "width": 518,
    "height": 29,
    "rotation": 0
  },
  {
    "type": "TEXT",
    "id": "P23L02",
    "rotation": 0,
    "textAlignment": {
      "horizontal": "JUSTIFIED",
      "vertical": "CENTER"
    },
    "textProperties": {
      "fontName": "Urbanist",
      "fontSize": 18,
      "isBold": true
    },
    "color": [
      "#000000"
    ]
  },
  {
    "type": "RECTANGLE",
    "id": "P23L01",
    "pageNumber": "23",
    "x": 41,
    "y": 78,
    "width": 518,
    "height": 219,
    "rotation": 0
  },
  {
    "type": "TEXT",
    "id": "P23L01",
    "rotation": 0,
    "textAlignment": {
      "horizontal": "JUSTIFIED",
      "vertical": "TOP"
    },
    "textProperties": {
      "fontName": "Urbanist",
      "fontSize": 17,
      "isBold": false
    },
    "color": [
      "#000000"
    ]
  },
  {
    "type": "RECTANGLE",
    "id": "P24L04",
    "pageNumber": "24",
    "x": 41,
    "y": 407,
    "width": 518,
    "height": 315,
    "rotation": 0
  },
  {
    "type": "TEXT",
    "id": "P24L04",
    "rotation": 0,
    "textAlignment": {
      "horizontal": "JUSTIFIED",
      "vertical": "TOP"
    },
    "textProperties": {
      "fontName": "Urbanist",
      "fontSize": 17,
      "isBold": false
    },
    "color": [
      "#000000"
    ]
  },
  {
    "type": "RECTANGLE",
    "id": "P24L03",
    "pageNumber": "24",
    "x": 41,
    "y": 347,
    "width": 518,
    "height": 43,
    "rotation": 0
  },
  {
    "type": "TEXT",
    "id": "P24L03",
    "rotation": 0,
    "textAlignment": {
      "horizontal": "JUSTIFIED",
      "vertical": "CENTER"
    },
    "textProperties": {
      "fontName": "Urbanist",
      "fontSize": 18,
      "isBold": true
    },
    "color": [
      "#000000"
    ]
  },
  {
    "type": "RECTANGLE",
    "id": "P24L02",
    "pageNumber": "24",
    "x": 41,
    "y": 152,
    "width": 518,
    "height": 170,
    "rotation": 0
  },
  {
    "type": "TEXT",
    "id": "P24L02",
    "rotation": 0,
    "textAlignment": {
      "horizontal": "JUSTIFIED",
      "vertical": "TOP"
    },
    "textProperties": {
      "fontName": "Urbanist",
      "fontSize": 17,
      "isBold": false
    },
    "color": [
      "#000000"
    ]
  },
  {
    "type": "RECTANGLE",
    "id": "P24L01",
    "pageNumber": "24",
    "x": 41,
    "y": 92,
    "width": 518,
    "height": 43,
    "rotation": 0
  },
  {
    "type": "TEXT",
    "id": "P24L01",
    "rotation": 0,
    "textAlignment": {
      "horizontal": "JUSTIFIED",
      "vertical": "CENTER"
    },
    "textProperties": {
      "fontName": "Urbanist",
      "fontSize": 18,
      "isBold": true
    },
    "color": [
      "#000000"
    ]
  },
  {
    "type": "RECTANGLE",
    "id": "P19L02",
    "pageNumber": "19",
    "x": 41,
    "y": 132,
    "width": 518,
    "height": 58,
    "rotation": 0
  },
  {
    "type": "TEXT",
    "id": "P19L02",
    "rotation": 0,
    "textAlignment": {
      "horizontal": "JUSTIFIED",
      "vertical": "TOP"
    },
    "textProperties": {
      "fontName": "Urbanist",
      "fontSize": 17,
      "isBold": false
    },
    "color": [
      "#000000"
    ]
  },
  {
    "type": "TEXT",
    "id": "P19L01",
    "rotation": 0,
    "textAlignment": {
      "horizontal": "JUSTIFIED",
      "vertical": "CENTER"
    },
    "textProperties": {
      "fontName": "Urbanist",
      "fontSize": 18,
      "isBold": true
    },
    "color": [
      "#000000"
    ]
  },
  {
    "type": "RECTANGLE",
    "id": "P19L01",
    "pageNumber": "19",
    "x": 41,
    "y": 89,
    "width": 518,
    "height": 29,
    "rotation": 0
  },
  {
    "type": "RECTANGLE",
    "id": "P20L02",
    "pageNumber": "20",
    "x": 41,
    "y": 132,
    "width": 518,
    "height": 58,
    "rotation": 0
  },
  {
    "type": "RECTANGLE",
    "id": "P20L01",
    "pageNumber": "20",
    "x": 41,
    "y": 89,
    "width": 518,
    "height": 29,
    "rotation": 0
  },
  {
    "type": "TEXT",
    "id": "P20L02",
    "rotation": 0,
    "textAlignment": {
      "horizontal": "JUSTIFIED",
      "vertical": "TOP"
    },
    "textProperties": {
      "fontName": "Urbanist",
      "fontSize": 17,
      "isBold": false
    },
    "color": [
      "#000000"
    ]
  },
  {
    "type": "TEXT",
    "id": "P20L01",
    "rotation": 0,
    "textAlignment": {
      "horizontal": "JUSTIFIED",
      "vertical": "CENTER"
    },
    "textProperties": {
      "fontName": "Urbanist",
      "fontSize": 18,
      "isBold": true
    },
    "color": [
      "#000000"
    ]
  }
]